odoo/addons/account_consolidation/README.rst
odoo/addons/account_consolidation/__init__.py
odoo/addons/account_consolidation/__manifest__.py
odoo/addons/account_consolidation/hooks.py
odoo/addons/account_consolidation/demo/company_a_demo.xml
odoo/addons/account_consolidation/demo/company_b_demo.xml
odoo/addons/account_consolidation/demo/company_demo.xml
odoo/addons/account_consolidation/demo/consolidation_demo.xml
odoo/addons/account_consolidation/demo/currency_demo.xml
odoo/addons/account_consolidation/i18n/account_consolidation.pot
odoo/addons/account_consolidation/i18n/es.po
odoo/addons/account_consolidation/i18n/hr.po
odoo/addons/account_consolidation/i18n/pt.po
odoo/addons/account_consolidation/i18n/pt_BR.po
odoo/addons/account_consolidation/models/__init__.py
odoo/addons/account_consolidation/models/account.py
odoo/addons/account_consolidation/models/account_move.py
odoo/addons/account_consolidation/models/company.py
odoo/addons/account_consolidation/models/consolidation_profile.py
odoo/addons/account_consolidation/models/res_config_settings.py
odoo/addons/account_consolidation/readme/CONFIGURE.rst
odoo/addons/account_consolidation/readme/DESCRIPTION.rst
odoo/addons/account_consolidation/readme/ROADMAP.rst
odoo/addons/account_consolidation/readme/USAGE.rst
odoo/addons/account_consolidation/security/account_consolidation_security.xml
odoo/addons/account_consolidation/security/ir.model.access.csv
odoo/addons/account_consolidation/security/res_groups.xml
odoo/addons/account_consolidation/static/description/icon.png
odoo/addons/account_consolidation/static/description/index.html
odoo/addons/account_consolidation/tests/__init__.py
odoo/addons/account_consolidation/tests/test_account_company_rules.py
odoo/addons/account_consolidation/tests/test_account_consolidation.py
odoo/addons/account_consolidation/views/account_move_line_view.xml
odoo/addons/account_consolidation/views/account_view.xml
odoo/addons/account_consolidation/views/company_consolidation_profile.xml
odoo12_addon_account_consolidation-12.0.1.0.0.99.dev30.dist-info/METADATA
odoo12_addon_account_consolidation-12.0.1.0.0.99.dev30.dist-info/WHEEL
odoo12_addon_account_consolidation-12.0.1.0.0.99.dev30.dist-info/top_level.txt
odoo12_addon_account_consolidation-12.0.1.0.0.99.dev30.dist-info/RECORD
